LICENSE.txt
README.rst
setup.cfg
setup.py
pysci/__init__.py
pysci/sci.py
pyscitxt.egg-info/PKG-INFO
pyscitxt.egg-info/SOURCES.txt
pyscitxt.egg-info/dependency_links.txt
pyscitxt.egg-info/top_level.txt