Metadata-Version: 2.1
Name: pyscitxt
Version: 0.0.1
Summary: pysci by ****
Home-page: https://github.com/drxprichkrup/pysci
Download-URL: https://github.com/drxprichkrup/pysci/archive/v0.0.1.zip
Author: drxprichkrup
Author-email: drxprichkrup@gmail.com
License: MIT
Keywords: pysci,pysci01,pysci02
Classifier: Development Status :: 3 - Alpha
Classifier: Intended Audience :: Education
Classifier: Topic :: Utilities
Classifier: License :: OSI Approved :: MIT License
Classifier: Programming Language :: Python :: 3
Classifier: Programming Language :: Python :: 3.4
Classifier: Programming Language :: Python :: 3.5
Classifier: Programming Language :: Python :: 3.6
Classifier: Programming Language :: Python :: 3.7
Classifier: Programming Language :: Python :: 3.8
Classifier: Programming Language :: Python :: 3.9
Classifier: Programming Language :: Python :: 3.10
License-File: LICENSE.txt
